silurian/__init__.py
silurian/client.py
silurian/core/__init__.py
silurian/core/api_error.py
silurian/core/client_wrapper.py
silurian/core/datetime_utils.py
silurian/core/file.py
silurian/core/force_multipart.py
silurian/core/http_client.py
silurian/core/http_response.py
silurian/core/http_sse/__init__.py
silurian/core/http_sse/_api.py
silurian/core/http_sse/_decoders.py
silurian/core/http_sse/_exceptions.py
silurian/core/http_sse/_models.py
silurian/core/jsonable_encoder.py
silurian/core/pydantic_utilities.py
silurian/core/query_encoder.py
silurian/core/remove_none_from_dict.py
silurian/core/request_options.py
silurian/core/serialization.py
silurian/cyclones/__init__.py
silurian/cyclones/client.py
silurian/cyclones/forecasts/__init__.py
silurian/cyclones/forecasts/client.py
silurian/cyclones/forecasts/raw_client.py
silurian/cyclones/raw_client.py
silurian/environment.py
silurian/errors/__init__.py
silurian/errors/unprocessable_entity_error.py
silurian/portfolios/__init__.py
silurian/portfolios/client.py
silurian/portfolios/raw_client.py
silurian/py.typed
silurian/types/__init__.py
silurian/types/base_model.py
silurian/types/cyclone_forecast_response.py
silurian/types/daily_conditions.py
silurian/types/daily_weather_response.py
silurian/types/daily_weather_response_units.py
silurian/types/feature.py
silurian/types/feature_collection.py
silurian/types/feature_geometry.py
silurian/types/feature_id.py
silurian/types/feature_properties.py
silurian/types/geo_location.py
silurian/types/geometry_collection.py
silurian/types/geometry_collection_geometries_item.py
silurian/types/gftus_base_units.py
silurian/types/gftus_hourly_conditions.py
silurian/types/gftus_hourly_weather_response.py
silurian/types/hourly_conditions.py
silurian/types/hourly_weather_response.py
silurian/types/hourly_weather_response_units.py
silurian/types/http_validation_error.py
silurian/types/imperial_units.py
silurian/types/line_string.py
silurian/types/line_string_coordinates_item.py
silurian-0.0.18.dist-info/METADATA
silurian-0.0.18.dist-info/WHEEL
silurian-0.0.18.dist-info/RECORD
